inter_api_connector/__init__.py
inter_api_connector/api.py
inter_api_connector/connector.py
inter_api_connector/error.py
inter_api_connector/objects.py
inter_api_connector/patch.py
inter_api_connector/utils.py
inter_api_connector-0.1.3.dist-info/LICENSE
inter_api_connector-0.1.3.dist-info/METADATA
inter_api_connector-0.1.3.dist-info/WHEEL
inter_api_connector-0.1.3.dist-info/top_level.txt
inter_api_connector-0.1.3.dist-info/RECORD
