Metadata-Version: 2.1
Name: inter_api_connector
Version: 0.1.3
Summary: Um conector não oficial para API do Banco Inter.
Home-page: https://github.com/LuizDMM/api-inter-python-connector
Author: LuizDMM
Author-email: luizdmmainart@gmail.com
License: MIT
Project-URL: Source, https://github.com/LuizDMM/api-inter-python-connector
Classifier: Development Status :: 2 - Pre-Alpha
Classifier: Intended Audience :: Developers
Classifier: License :: OSI Approved :: MIT License
Classifier: Natural Language :: Portuguese (Brazilian)
Classifier: Programming Language :: Python :: 3
Classifier: Programming Language :: Python :: 3 :: Only
Classifier: Programming Language :: Python :: 3.8
Classifier: Programming Language :: Python :: 3.9
Classifier: Programming Language :: Python :: 3.10
Classifier: Programming Language :: Python :: 3.11
Classifier: Programming Language :: Python :: 3.12
Classifier: Operating System :: OS Independent
Classifier: Topic :: Office/Business :: Financial
Requires-Python: >=3.8
License-File: LICENSE
Requires-Dist: requests >=2.31.0
Requires-Dist: pyOpenSSL >=23.3.0
Requires-Dist: cryptography >=1.3.4
Requires-Dist: idna >=2.0
Provides-Extra: dev
Requires-Dist: build >=1.0.3 ; extra == 'dev'
Requires-Dist: sphinx ; extra == 'dev'
